gws/__init__.py
gws/__main__.py
gws/py.typed
gridworks_ws-0.0.4.dist-info/LICENSE
gridworks_ws-0.0.4.dist-info/METADATA
gridworks_ws-0.0.4.dist-info/WHEEL
gridworks_ws-0.0.4.dist-info/entry_points.txt
gridworks_ws-0.0.4.dist-info/RECORD
