Metadata-Version: 2.1
Name: gridworks-ws
Version: 0.0.4
Summary: GridWorks Weather Service
Home-page: https://github.com/thegridelectric/gridworks-ws
License: MIT
Author: Jessica Millar
Author-email: jmillar@gridworks-consulting.com
Requires-Python: >=3.11,<4.0
Classifier: Development Status :: 2 - Pre-Alpha
Classifier: License :: OSI Approved :: MIT License
Classifier: Programming Language :: Python :: 3
Classifier: Programming Language :: Python :: 3.11
Classifier: Programming Language :: Python :: 3.12
Requires-Dist: click (>=8.0.1)
Project-URL: Changelog, https://github.com/thegridelectric/gridworks-ws/releases
Project-URL: Documentation, https://gridworks-ws.readthedocs.io
Project-URL: Repository, https://github.com/thegridelectric/gridworks-ws
